pyufoled/__init__.py
pyufoled/bytecodes.py
pyufoled/ld686.py
pyufoled/protocol.py
pyufoled-0.0.2.dist-info/LICENSE
pyufoled-0.0.2.dist-info/METADATA
pyufoled-0.0.2.dist-info/WHEEL
pyufoled-0.0.2.dist-info/top_level.txt
pyufoled-0.0.2.dist-info/RECORD
