Metadata-Version: 2.1
Name: pyufoled
Version: 0.0.2
Summary: A Python3 wrapper for LD686-compatible LED controllers.
Home-page: https://github.com/ErikMayrhofer/pyufoled
Author: Erik Mayrhofer
Author-email: obyoxar+pypi@gmail.com
License: UNKNOWN
Platform: UNKNOWN
Classifier: License :: OSI Approved :: MIT License
Classifier: Programming Language :: Python :: 3
Classifier: Topic :: Home Automation
Classifier: Operating System :: OS Independent
